Ecmascript6RumenDisanban/README.md
Ecmascript6RumenDisanban/__init__.py
Ecmascript6RumenDisanban/__main__.py
Ecmascript6RumenDisanban/file.epub
Ecmascript6RumenDisanban/index.html
Ecmascript6RumenDisanban/css/__init__.py
Ecmascript6RumenDisanban/css/annotations.css
Ecmascript6RumenDisanban/css/main.css
Ecmascript6RumenDisanban/css/normalize.css
Ecmascript6RumenDisanban/css/popup.css
Ecmascript6RumenDisanban/font/__init__.py
Ecmascript6RumenDisanban/font/fontello.eot
Ecmascript6RumenDisanban/font/fontello.svg
Ecmascript6RumenDisanban/font/fontello.ttf
Ecmascript6RumenDisanban/font/fontello.woff
Ecmascript6RumenDisanban/img/__init__.py
Ecmascript6RumenDisanban/img/annotator-glyph-sprite.png
Ecmascript6RumenDisanban/img/annotator-icon-sprite.png
Ecmascript6RumenDisanban/img/apple-touch-icon.png
Ecmascript6RumenDisanban/img/cancelfullscreen.png
Ecmascript6RumenDisanban/img/close.png
Ecmascript6RumenDisanban/img/fullscreen.png
Ecmascript6RumenDisanban/img/loader.gif
Ecmascript6RumenDisanban/img/menu-icon.png
Ecmascript6RumenDisanban/img/save.png
Ecmascript6RumenDisanban/img/saved.png
Ecmascript6RumenDisanban/img/settings-s.png
Ecmascript6RumenDisanban/img/settings.png
Ecmascript6RumenDisanban/img/star.png
Ecmascript6RumenDisanban/js/__init__.py
Ecmascript6RumenDisanban/js/epub.js
Ecmascript6RumenDisanban/js/epub.min.js
Ecmascript6RumenDisanban/js/epub.min.map
Ecmascript6RumenDisanban/js/hooks.min.js
Ecmascript6RumenDisanban/js/hooks.min.map
Ecmascript6RumenDisanban/js/reader.js
Ecmascript6RumenDisanban/js/reader.js.map
Ecmascript6RumenDisanban/js/reader.min.js
Ecmascript6RumenDisanban/js/reader.min.map
Ecmascript6RumenDisanban/js/hooks/__init__.py
Ecmascript6RumenDisanban/js/hooks/extensions/__init__.py
Ecmascript6RumenDisanban/js/hooks/extensions/highlight.js
Ecmascript6RumenDisanban/js/libs/__init__.py
Ecmascript6RumenDisanban/js/libs/jquery.min.js
Ecmascript6RumenDisanban/js/libs/localforage.min.js
Ecmascript6RumenDisanban/js/libs/screenfull.js
ecmascript_6_rumen_disanban-2024.3.2.0.dist-info/METADATA
ecmascript_6_rumen_disanban-2024.3.2.0.dist-info/WHEEL
ecmascript_6_rumen_disanban-2024.3.2.0.dist-info/entry_points.txt
ecmascript_6_rumen_disanban-2024.3.2.0.dist-info/top_level.txt
ecmascript_6_rumen_disanban-2024.3.2.0.dist-info/RECORD
